bokeh_pipe/__init__.py
bokeh_pipe/bokeh_pipe.py
bokeh_pipe/bokeh_plot.py
bokeh_pipe/bokeh_utilities.py
bokeh_pipe/contourmerc.csv
bokeh_pipe/crime_filtered_data.csv
bokeh_pipe/hull.py
bokeh_pipe/streamlinef.py
cynet/__init__.py
cynet/__init__.pyc
cynet/cynet.py
cynet/cynet.pyc
cynet/bin/XgenESeSS
cynet/bin/cynet
cynet/bin/flexroc
cynet-2.0.4.data/data/example_cynet/cynet_crime_example.pdf
cynet-2.0.4.data/data/example_cynet/example3.zip
cynet-2.0.4.data/data/example_cynet/example2/config_pypi.yaml
cynet-2.0.4.data/data/example_cynet/example2/terrortest_small.py
cynet-2.0.4.data/data/example_cynet/example2/models/empty.txt
cynet-2.0.4.data/data/example_cynet/example2/split/empty.txt
cynet-2.0.4.data/data/example_cynet/example2/triplet/empty.txt
cynet-2.0.4.data/scripts/print_help.py
cynet_utils/concat_model_json_read.py
cynet_utils/spatial.py
viscynet/__init__.py
viscynet/viscynet.py
cynet-2.0.4.dist-info/LICENSE.txt
cynet-2.0.4.dist-info/METADATA
cynet-2.0.4.dist-info/WHEEL
cynet-2.0.4.dist-info/top_level.txt
cynet-2.0.4.dist-info/RECORD
