Metadata-Version: 2.1
Name: cynet
Version: 2.0.4
Summary: Learning Point Processes Using Deep Granger Nets
Home-page: https://github.com/zeroknowledgediscovery/
Download-URL: https://github.com/zeroknowledgediscovery/Cynet/archive/2.0.4.tar.gz
Author: zed.uchicago.edu
Author-email: ishanu@uchicago.edu
License: LICENSE.txt
Keywords: spatial,temporal,inference,statistical,causality
Classifier: Development Status :: 4 - Beta
Classifier: Intended Audience :: Developers
Classifier: Intended Audience :: Science/Research
Classifier: Topic :: Scientific/Engineering :: Information Analysis
Classifier: Topic :: Software Development :: Libraries
Classifier: License :: OSI Approved :: MIT License
Classifier: Programming Language :: Python :: 3
Requires-Python: ==3.*
License-File: LICENSE.txt
Requires-Dist: numpy (>=1.6)
Requires-Dist: pandas (>=0.22.0)
Requires-Dist: matplotlib (>=2.0.2)
Requires-Dist: scipy (>=0.18.1)
Requires-Dist: tqdm (>=4.11.2)
Requires-Dist: seaborn (>=0.8.0)
Requires-Dist: sodapy (>=1.4.6)
Requires-Dist: pyproj (>=1.9.5.1)
Requires-Dist: pyshp (>=1.2.12)
Requires-Dist: haversine (>=0.4.5)
Requires-Dist: joblib (>=0.12.2)
